{"cameraMode":{"drawMode":0,"name":"Shaded","section":"Shading Mode"},"sceneLighting":true,"audioPlay":false,"sceneViewState":{"m_AlwaysRefresh":false,"showFog":true,"showSkybox":true,"showFlares":true,"showImageEffects":true,"showParticleSystems":true,"showVisualEffectGraphs":true,"m_FxEnabled":true},"in2DMode":false,"pivot":{"x":0.8902968168258667,"y":2.6585159301757814,"z":-2.250042200088501},"rotation":{"x":-0.03279981017112732,"y":0.959587574005127,"z":-0.12624461948871613,"w":-0.24932022392749787},"size":0.0022301950957626106,"orthographic":false}